CHANGELOG.txt
HISTORY.txt
MANIFEST.in
README.txt
setup.cfg
setup.py
cp/__init__.py
cp.recipe.cmd.egg-info/PKG-INFO
cp.recipe.cmd.egg-info/SOURCES.txt
cp.recipe.cmd.egg-info/dependency_links.txt
cp.recipe.cmd.egg-info/entry_points.txt
cp.recipe.cmd.egg-info/namespace_packages.txt
cp.recipe.cmd.egg-info/not-zip-safe
cp.recipe.cmd.egg-info/requires.txt
cp.recipe.cmd.egg-info/top_level.txt
cp/recipe/__init__.py
cp/recipe/cmd/__init__.py
cp/recipe/cmd/tests/__init__.py
cp/recipe/cmd/tests/test_cmddocs.py