Metadata-Version: 1.1
Name: cp.recipe.cmd
Version: 0.5
Summary: ZC Buildout recipe to execute commands in it's own shell
Home-page: https://bitbucket.org/csawyer/cp.recipe.cmd/overview
Author: YUHSD #70
Author-email: csawyer@yumaed.org
License: GPL
Keywords: buildout,zc.buildout,recipe
Platform: UNKNOWN
Classifier: Programming Language :: Python
Classifier: Topic :: Software Development :: Libraries :: Python Modules
Classifier: Framework :: Buildout
